{
  "main": {
    "id": "623516aafdf1e742",
    "type": "split",
    "children": [
      {
        "id": "7261e021f823400c",
        "type": "tabs",
        "children": [
          {
            "id": "963727a92a159374",
            "type": "leaf",
            "state": {
              "type": "empty",
              "state": {},
              "icon": "lucide-file",
              "title": "Nova aba"
            }
          }
        ]
      }
    ],
    "direction": "vertical"
  },
  "left": {
    "id": "8d1079cdb022c399",
    "type": "split",
    "children": [
      {
        "id": "7a9d8ac166f0aaf6",
        "type": "tabs",
        "children": [
          {
            "id": "9aefdc939502ecc1",
            "type": "leaf",
            "state": {
              "type": "file-explorer",
              "state": {
                "sortOrder": "alphabetical",
                "autoReveal": false
              },
              "icon": "lucide-folder-closed",
              "title": "Explorador de arquivos"
            }
          },
          {
            "id": "decf6ae36242d1de",
            "type": "leaf",
            "state": {
              "type": "search",
              "state": {
                "query": "",
                "matchingCase": false,
                "explainSearch": false,
                "collapseAll": false,
                "extraContext": false,
                "sortOrder": "alphabetical"
              },
              "icon": "lucide-search",
              "title": "Procurar"
            }
          },
          {
            "id": "8e08d011ac112758",
            "type": "leaf",
            "state": {
              "type": "bookmarks",
              "state": {},
              "icon": "lucide-bookmark",
              "title": "Marcadores"
            }
          }
        ]
      }
    ],
    "direction": "horizontal",
    "width": 300
  },
  "right": {
    "id": "ad8cd0d1e6375979",
    "type": "split",
    "children": [
      {
        "id": "ad5ab7b8529042cb",
        "type": "tabs",
        "children": [
          {
            "id": "b8f6d9bfd6d96b63",
            "type": "leaf",
            "state": {
              "type": "backlink",
              "state": {
                "collapseAll": false,
                "extraContext": false,
                "sortOrder": "alphabetical",
                "showSearch": false,
                "searchQuery": "",
                "backlinkCollapsed": false,
                "unlinkedCollapsed": true
              },
              "icon": "links-coming-in",
              "title": "Backlinks"
            }
          },
          {
            "id": "a558dd4a3fdc592f",
            "type": "leaf",
            "state": {
              "type": "outgoing-link",
              "state": {
                "linksCollapsed": false,
                "unlinkedCollapsed": true
              },
              "icon": "links-going-out",
              "title": "Links de saída"
            }
          },
          {
            "id": "94db34b25fb431e5",
            "type": "leaf",
            "state": {
              "type": "tag",
              "state": {
                "sortOrder": "frequency",
                "useHierarchy": true,
                "showSearch": false,
                "searchQuery": ""
              },
              "icon": "lucide-tags",
              "title": "Tags"
            }
          },
          {
            "id": "066ad65738a08c16",
            "type": "leaf",
            "state": {
              "type": "outline",
              "state": {
                "followCursor": false,
                "showSearch": false,
                "searchQuery": ""
              },
              "icon": "lucide-list",
              "title": "Sumário"
            }
          }
        ]
      }
    ],
    "direction": "horizontal",
    "width": 300,
    "collapsed": true
  },
  "left-ribbon": {
    "hiddenItems": {
      "switcher:Abrir a troca rápida": false,
      "graph:Abrir visualização em gráfico": false,
      "canvas:Criar novo canvas": false,
      "daily-notes:Abrir a nota de hoje": false,
      "templates:Inserir modelo": false,
      "command-palette:Abrir paleta de comandos": false
    }
  },
  "active": "963727a92a159374",
  "lastOpenFiles": [
    "Notas Permanentes/Outros.md",
    "Notas Permanentes/Educação e Aprendizagem/Livros.md",
    "Notas Literárias/Empreendedorismo/Treinamentos/FIA - Estratégia Empresarial/FIA - Estratégia Empresarial.md"
  ]
}